shipgrav/__init__.py
shipgrav/database.toml
shipgrav/grav.py
shipgrav/io.py
shipgrav/nav.py
shipgrav/utils.py
shipgrav/tests/__init__.py
shipgrav/tests/__main__.py
shipgrav/tests/test_grav_data.py
shipgrav/tests/test_grav_nodata.py
shipgrav/tests/test_io.py
shipgrav/tests/test_nav.py
shipgrav/tests/test_utils.py
shipgrav/tests/ex_files/AT01_bgm.BGM
shipgrav/tests/ex_files/AT01_nav.gps
shipgrav/tests/ex_files/AT05_01_bgm.RGS
shipgrav/tests/ex_files/DGStest_laptop.dat
shipgrav/tests/ex_files/IXBlue.yaml
shipgrav/tests/ex_files/MGL2003_bgm.y2020d244
shipgrav/tests/ex_files/MGL2003_nav.y2020d244
shipgrav/tests/ex_files/NBP_2301_nav.d013
shipgrav/tests/ex_files/RR2212_bgm.txt
shipgrav/tests/ex_files/RR2212_nav.txt
shipgrav/tests/ex_files/SR2302_nav.raw
shipgrav/tests/ex_files/SR2312_dgs_raw.txt
shipgrav/tests/ex_files/SR2312_mru.txt
shipgrav/tests/ex_files/TN400_bgm.Raw
shipgrav/tests/ex_files/TN400_dgs_proc.Raw
shipgrav/tests/ex_files/TN400_dgs_raw.Raw
shipgrav/tests/ex_files/TN400_nav.Raw
shipgrav-1.0.6.dist-info/METADATA
shipgrav-1.0.6.dist-info/WHEEL
shipgrav-1.0.6.dist-info/licenses/LICENSE
shipgrav-1.0.6.dist-info/RECORD
