Metadata-Version: 2.3
Name: shipgrav
Version: 1.0.6
Summary: Functions for marine gravity data processing and reduction
Author-email: "Hannah F. Mark" <hmark@whoi.edu>
Maintainer-email: "Hannah F. Mark" <hmark@whoi.edu>
Keywords: UNOLS,gravimetry,marine gravity
Classifier: License :: OSI Approved :: GNU General Public License v3 (GPLv3)
Classifier: Operating System :: OS Independent
Classifier: Programming Language :: Python :: 3
Requires-Dist: numpy
Requires-Dist: pandas
Requires-Dist: pyyaml
Requires-Dist: scipy
Requires-Dist: statsmodels
Requires-Dist: tomli
Requires-Dist: tqdm
Provides-Extra: examples
Requires-Dist: geographiclib; extra == 'examples'
Requires-Dist: jupyterlab; extra == 'examples'
Requires-Dist: jupytext; extra == 'examples'
Requires-Dist: matplotlib; extra == 'examples'
Requires-Dist: pooch; extra == 'examples'
